setup.py
Babelian.egg-info/PKG-INFO
Babelian.egg-info/SOURCES.txt
Babelian.egg-info/dependency_links.txt
Babelian.egg-info/not-zip-safe
Babelian.egg-info/pbr.json
Babelian.egg-info/top_level.txt
babelian/__init__.py
babelian/babelian.py
bin/td