Metadata-Version: 1.1
Name: Babelian
Version: 1.1
Summary: The Babelian is a dictionary of a Terminal.
Home-page: https://github.com/cryptosan/babelian
Author: Cryptos An
Author-email: frostlabx@gmail.com
License: MIT
Platform: any
Classifier: Environment :: Console
Classifier: Intended Audience :: Education
Classifier: License :: OSI Approved :: MIT License
Classifier: Operating System :: MacOS
Classifier: Operating System :: POSIX :: Linux
Classifier: Programming Language :: Python
Classifier: Programming Language :: Python :: 2.7
Classifier: Programming Language :: Python :: 3
Classifier: Programming Language :: Python :: 3.4
Classifier: Topic :: Education
